openkat/__init__.py
openkat/__main__.py
openkat/account/__init__.py
openkat/account/admin.py
openkat/account/apps.py
openkat/account/forms/__init__.py
openkat/account/forms/account_setup.py
openkat/account/forms/login.py
openkat/account/forms/password_reset.py
openkat/account/forms/token.py
openkat/account/models.py
openkat/account/templates/account_detail.html
openkat/account/templates/login.html
openkat/account/templates/password_reset.html
openkat/account/templates/password_reset_confirm.html
openkat/account/templates/password_reset_done.html
openkat/account/templates/password_reset_email.html
openkat/account/templates/password_reset_subject.txt
openkat/account/templates/recover_email.html
openkat/account/urls.py
openkat/account/validators.py
openkat/account/views/__init__.py
openkat/account/views/account.py
openkat/account/views/login.py
openkat/account/views/password_reset.py
openkat/account/views/recover_email.py
openkat/assets/dist/app.css
openkat/assets/dist/app.css.map
openkat/assets/dist/app.js
openkat/assets/dist/app.js.map
openkat/assets/dist/graph.css
openkat/assets/dist/graph.css.map
openkat/assets/dist/graph.js
openkat/assets/dist/graph.js.map
openkat/assets/dist/manon.js
openkat/assets/dist/manon.js.map
openkat/assets/dist/paw-active.baf57460.svg
openkat/assets/dist/paw-inactive.bb233e49.svg
openkat/assets/dist/tabler-icons.049fe672.svg
openkat/assets/dist/tabler-icons.6d5b56e4.ttf
openkat/assets/dist/tabler-icons.729ada4a.woff2
openkat/assets/dist/tabler-icons.7aa644ea.woff
openkat/assets/dist/tabler-icons.87a11f26.eot
openkat/assets/img/graph.png
openkat/assets/img/kat_logo.png
openkat/assets/img/keiko.jpg
openkat/assets/img/loader/ball.svg
openkat/assets/img/loader/body.svg
openkat/assets/img/loader/ear_left.svg
openkat/assets/img/loader/ear_right.svg
openkat/assets/img/loader/head.svg
openkat/assets/img/loader/paw.svg
openkat/assets/img/loader/tail.svg
openkat/assets/img/loader/yarn.svg
openkat/assets/img/paw-active.svg
py_openkat-1.2.2.post1.dist-info/LICENSE
py_openkat-1.2.2.post1.dist-info/WHEEL
py_openkat-1.2.2.post1.dist-info/METADATA
py_openkat-1.2.2.post1.dist-info/RECORD
