Metadata-Version: 2.1
Name: py-openkat
Version: 1.2.2.post1
Summary: A lightweight version of OpenKAT.
Home-page: https://github.com/Donnype/py-openkat
Keywords: OpenKAT,Security Analysis
Author: Donny Peeters
Author-email: donny.peeters@hotmail.com
Maintainer: Donny Peeters
Maintainer-email: donny.peeters@hotmail.com
Requires-Python: >=3.8,<4.0
Classifier: Programming Language :: Python :: 3
Classifier: Programming Language :: Python :: 3.8
Classifier: Programming Language :: Python :: 3.9
Classifier: Programming Language :: Python :: 3.10
Requires-Dist: Django (==3.2.15)
Requires-Dist: SQLAlchemy (>=1.4.41,<2.0.0)
Requires-Dist: ares (>=0.7.1)
Requires-Dist: beautifulsoup4 (>=4.11.1)
Requires-Dist: colorama (>=0.4.5)
Requires-Dist: cryptography (>=3.4.3)
Requires-Dist: cwe (>=1.6)
Requires-Dist: django-csp (>=3.7)
Requires-Dist: django-markdownify (>=0.9.1)
Requires-Dist: django-otp (>=1.1.3)
Requires-Dist: django-password-validators (>=1.7.0)
Requires-Dist: django-two-factor-auth (>=1.14.0)
Requires-Dist: dnspython (>=2.1.0)
Requires-Dist: docker (>=6.0.0,<7.0.0)
Requires-Dist: forcediphttpsadapter (>=1.0.2)
Requires-Dist: mmh3 (>=3.0.0,<4.0.0)
Requires-Dist: phonenumbers (>=8.12.55,<9.0.0)
Requires-Dist: pybinaryedge (>=0.5)
Requires-Dist: pydantic (>=1.8.2)
Requires-Dist: pynetdicom (>=2.0.2,<3.0.0)
Requires-Dist: python-Wappalyzer (>=0.3.1)
Requires-Dist: python-gettext (>=4.1,<5.0)
Requires-Dist: python-libnmap (>=0.7.3)
Requires-Dist: requests (>=2.26.0,<3.0.0)
Requires-Dist: shodan (>=1.25.0)
Requires-Dist: wpscan-out-parse (>=1.9.3)
Project-URL: Repository, https://github.com/Donnype/py-openkat
